[
  {
    "excerpt": null,
    "publishedAt": null,
    "slug": {
      "_type": "slug",
      "current": "test-web"
    },
    "title": "webサイトの更新をチェックしています"
  },
  {
    "excerpt": null,
    "publishedAt": "2025-07-03T03:00:00.000Z",
    "slug": {
      "_type": "slug",
      "current": "new-website"
    },
    "title": "WEBサイトリニューアルのお知らせ"
  },
  {
    "excerpt": null,
    "publishedAt": "2025-07-02T15:15:00.000Z",
    "slug": {
      "_type": "slug",
      "current": "test6"
    },
    "title": "テスト投稿7です！"
  },
  {
    "excerpt": null,
    "publishedAt": "2025-07-02T15:00:00.000Z",
    "slug": {
      "_type": "slug",
      "current": "test5"
    },
    "title": "テスト5"
  }
]